uuyoupinapi/__init__.py
uuyoupinapi-0.1.2.dist-info/LICENSE
uuyoupinapi-0.1.2.dist-info/METADATA
uuyoupinapi-0.1.2.dist-info/WHEEL
uuyoupinapi-0.1.2.dist-info/top_level.txt
uuyoupinapi-0.1.2.dist-info/RECORD
