Metadata-Version: 2.1
Name: uuyoupinapi
Version: 0.1.2
Summary: 悠悠有品API
Home-page: https://github.com/jiajiaxd/uuyoupinapi
Author: jiajiaxd
Author-email: i@jiajiaxd.com
License: UNKNOWN
Platform: UNKNOWN
Classifier: Programming Language :: Python :: 3
Classifier: Operating System :: OS Independent
Classifier: License :: OSI Approved :: GNU General Public License v3 (GPLv3)
License-File: LICENSE
